code_assembler/__init__.py
code_assembler/__main__.py
code_assembler/analyzers.py
code_assembler/cli.py
code_assembler/config.py
code_assembler/constants.py
code_assembler/core.py
code_assembler/file_io.py
code_assembler/formatters.py
code_assembler/interactive.py
code_assembler/utils.py
code_assembler/templates/main_header.md.j2
code_assembler/templates/components/architecture.md.j2
code_assembler/templates/components/file_block.md.j2
code_assembler/templates/components/readme_context.md.j2
code_assembler/templates/components/stats_table.md.j2
code_assembler/templates/components/toc.md.j2
code_assembler_pro-4.2.1.dist-info/METADATA
code_assembler_pro-4.2.1.dist-info/WHEEL
code_assembler_pro-4.2.1.dist-info/entry_points.txt
code_assembler_pro-4.2.1.dist-info/top_level.txt
code_assembler_pro-4.2.1.dist-info/RECORD
