Metadata-Version: 2.4
Name: code-assembler-pro
Version: 4.2.1
Summary: Consolidate your codebase into structured Markdown context for LLMs (Claude, GPT, Gemini).
Author-email: Xavier Mehaut <xavier.mehaut@gmail.com>
License: MIT
Project-URL: Homepage, https://github.com/xmehaut/code-assembler-pro
Project-URL: Documentation, https://github.com/xmehaut/code-assembler-pro#readme
Project-URL: Repository, https://github.com/xmehaut/code-assembler-pro
Project-URL: Issues, https://github.com/xmehaut/code-assembler-pro/issues
Project-URL: Changelog, https://github.com/xmehaut/code-assembler-pro/blob/main/CHANGELOG.md
Keywords: llm,context,codebase,markdown,ai-engineering,prompt-engineering
Classifier: Programming Language :: Python :: 3
Classifier: Programming Language :: Python :: 3.9
Classifier: Programming Language :: Python :: 3.10
Classifier: Programming Language :: Python :: 3.11
Classifier: Programming Language :: Python :: 3.12
Classifier: Operating System :: OS Independent
Classifier: Topic :: Software Development :: Documentation
Classifier: Topic :: Text Processing :: Markup :: Markdown
Classifier: Intended Audience :: Developers
Classifier: Development Status :: 5 - Production/Stable
Requires-Python: >=3.9
Requires-Dist: chardet>=5.0.0
Requires-Dist: jinja2>=3.1.0
